{
	"partitions" : [
		{
			"name" : "Top",
			"pins" : [
				{
					"name" : "led",
					"strict" : false
				},
				{
					"name" : "led_test",
					"strict" : false
				},
				{
					"name" : "clk",
					"strict" : false
				},
				{
					"name" : "start",
					"strict" : false
				},
				{
					"name" : "reset",
					"strict" : false
				},
				{
					"name" : "sw[0]",
					"strict" : false
				},
				{
					"name" : "sw[1]",
					"strict" : false
				},
				{
					"name" : "sw[2]",
					"strict" : false
				}
			]
		}
	]
}